README.md
setup.py
pulumi_nutanix/__init__.py
pulumi_nutanix/_inputs.py
pulumi_nutanix/_utilities.py
pulumi_nutanix/access_control_policy.py
pulumi_nutanix/address_group.py
pulumi_nutanix/address_groups_v2.py
pulumi_nutanix/associate_category_to_volume_group_v2.py
pulumi_nutanix/authorization_policy_v2.py
pulumi_nutanix/category_key.py
pulumi_nutanix/category_v2.py
pulumi_nutanix/category_value.py
pulumi_nutanix/cluster_add_node_v2.py
pulumi_nutanix/cluster_v2.py
pulumi_nutanix/clusters_discover_unconfigured_nodes_v2.py
pulumi_nutanix/clusters_unconfigured_node_networks_v2.py
pulumi_nutanix/deploy_templates_v2.py
pulumi_nutanix/directory_services_v2.py
pulumi_nutanix/floating_ip.py
pulumi_nutanix/floating_ip_v2.py
pulumi_nutanix/foundation_central_api_keys.py
pulumi_nutanix/foundation_central_image_cluster.py
pulumi_nutanix/foundation_image.py
pulumi_nutanix/foundation_image_nodes.py
pulumi_nutanix/foundation_ipmi_config.py
pulumi_nutanix/get_access_control_policies.py
pulumi_nutanix/get_access_control_policy.py
pulumi_nutanix/get_address_group.py
pulumi_nutanix/get_address_group_v2.py
pulumi_nutanix/get_address_groups.py
pulumi_nutanix/get_address_groups_v2.py
pulumi_nutanix/get_assert_helper.py
pulumi_nutanix/get_authorization_policies_v2.py
pulumi_nutanix/get_authorization_policy_v2.py
pulumi_nutanix/get_blueprint_runtime_editables.py
pulumi_nutanix/get_categories_v2.py
pulumi_nutanix/get_category_key.py
pulumi_nutanix/get_category_v2.py
pulumi_nutanix/get_certificate_v2.py
pulumi_nutanix/get_certificates_v2.py
pulumi_nutanix/get_cluster.py
pulumi_nutanix/get_cluster_v2.py
pulumi_nutanix/get_clusters.py
pulumi_nutanix/get_clusters_v2.py
pulumi_nutanix/get_directory_service_v2.py
pulumi_nutanix/get_directory_services_v2.py
pulumi_nutanix/get_floating_ip.py
pulumi_nutanix/get_floating_ip_v2.py
pulumi_nutanix/get_floating_ips.py
pulumi_nutanix/get_floating_ips_v2.py
pulumi_nutanix/get_foundation_central_api_keys.py
pulumi_nutanix.egg-info/PKG-INFO
pulumi_nutanix.egg-info/SOURCES.txt
pulumi_nutanix.egg-info/dependency_links.txt
pulumi_nutanix.egg-info/not-zip-safe
pulumi_nutanix.egg-info/requires.txt
pulumi_nutanix.egg-info/top_level.txt
