Metadata-Version: 2.1
Name: pulumi-nutanix
Version: 0.10.0
Summary: A Pulumi package for creating and managing Nutanix cloud resources.
Home-page: https://github.com/pierskarsenbarg/pulumi-nutanix
License: Apache-2.0
Project-URL: Repository, https://github.com/pierskarsenbarg/pulumi-nutanix
Keywords: pulumi nutanix category/cloud
Requires-Python: >=3.9
